adam_mini/__init__.py
adam_mini/adam_mini.py
adam_mini-1.1.1.dist-info/METADATA
adam_mini-1.1.1.dist-info/WHEEL
adam_mini-1.1.1.dist-info/licenses/LICENSE
adam_mini-1.1.1.dist-info/RECORD
