Metadata-Version: 2.3
Name: adam_mini
Version: 1.1.1
Summary: Adam-mini Optimizer
Project-URL: Homepage, https://github.com/zyushun/Adam-mini
Project-URL: Issues, https://github.com/zyushun/Adam-mini/issues
Author-email: Yushun Zhang <yushunzhang@link.cuhk.edu.cn>, Congliang Chen <congliangchen@link.cuhk.edu.cn>, Ziniu Li <ziniuli@link.cuhk.edu.cn>, Tian Ding <dingtian@sribd.cn>, Chenwei Wu <cwwu@cs.duke.edu>, "Diederik P. Kingma" <dpkingma@gmail.com>, Yinyu Ye <yyye@stanford.edu>, Zhi-Quan Luo <luozq@cuhk.edu.cn>, Ruoyu Sun <sunruoyu@cuhk.edu.cn>
Classifier: License :: OSI Approved :: MIT License
Classifier: Operating System :: OS Independent
Classifier: Programming Language :: Python :: 3
Requires-Python: >=3.8
